Metadata-Version: 2.4
Name: adafruit-circuitpython-lsm9ds1
Version: 2.1.26
Summary: CircuitPython library for LSM9DS1 accelerometer, magnetometer, gyroscope.
Author-email: Adafruit Industries <circuitpython@adafruit.com>
License: MIT
Project-URL: Homepage, https://github.com/adafruit/Adafruit_CircuitPython_LSM9DS1
Keywords: adafruit,accelerometer,magnetometer,gyroscope,lsm9ds1breakout,hardware,micropython,circuitpython
Classifier: Intended Audience :: Developers
Classifier: Topic :: Software Development :: Libraries
Classifier: Topic :: Software Development :: Embedded Systems
Classifier: Topic :: System :: Hardware
Classifier: License :: OSI Approved :: MIT License
Classifier: Programming Language :: Python :: 3
License-File: LICENSE
Requires-Dist: Adafruit-Blinka
Requires-Dist: adafruit-circuitpython-busdevice
Requires-Dist: adafruit-circuitpython-typing
Provides-Extra: optional
Dynamic: license-file
